datadraw/__init__.py
datadraw/sds.py
datadraw/sdsdt.py
datadraw/sdsmisc.py
datadraw-0.7.1.dist-info/LICENSE.txt
datadraw-0.7.1.dist-info/METADATA
datadraw-0.7.1.dist-info/WHEEL
datadraw-0.7.1.dist-info/top_level.txt
datadraw-0.7.1.dist-info/RECORD
